xrpatcher/__init__.py
xrpatcher/_src/__init__.py
xrpatcher/_src/base.py
xrpatcher/_src/exceptions.py
xrpatcher/_src/test_base.py
xrpatcher/_src/test_utils.py
xrpatcher/_src/utils.py
xrpatcher-0.0.1.dist-info/LICENSE
xrpatcher-0.0.1.dist-info/METADATA
xrpatcher-0.0.1.dist-info/WHEEL
xrpatcher-0.0.1.dist-info/RECORD
