Metadata-Version: 2.1
Name: xrpatcher
Version: 0.0.1
Summary: A ML-oriented generic patcher for xarray data structures.
Home-page: https://github.com/jejjohnson/xrpatcher
License: MIT
Keywords: xarray,patcher,pytorch
Author: J. Emmanuel Johnson
Author-email: jemanjohnson34@gmail.com
Requires-Python: >=3.8,<3.12
Classifier: Development Status :: 2 - Pre-Alpha
Classifier: Intended Audience :: Science/Research
Classifier: License :: OSI Approved :: MIT License
Classifier: Natural Language :: English
Classifier: Programming Language :: Python :: 3
Classifier: Programming Language :: Python :: 3.8
Classifier: Programming Language :: Python :: 3.9
Classifier: Programming Language :: Python :: 3.10
Classifier: Programming Language :: Python :: 3.11
Classifier: Topic :: Scientific/Engineering
Classifier: Topic :: Software Development :: Libraries
Requires-Dist: tqdm (>=4.65.0,<5.0.0)
Requires-Dist: urllib3 (==1.26.15)
Requires-Dist: xarray (>=2022.3)
Project-URL: Repository, https://github.com/jejjohnson/xrpatcher
